LICENSE
MANIFEST.in
README.rst
requirements.txt
setup.py
django_requests_panel.egg-info/PKG-INFO
django_requests_panel.egg-info/SOURCES.txt
django_requests_panel.egg-info/dependency_links.txt
django_requests_panel.egg-info/requires.txt
django_requests_panel.egg-info/top_level.txt
requests_panel/__init__.py
requests_panel/panels.py
requests_panel/requests_wrapper.py
requests_panel/tests.py
requests_panel/templates/requests_panel/requests_panel.html