Metadata-Version: 1.0
Name: django-requests-panel
Version: 0.4.0
Summary: A Django Debug Toolbar panel for requests
Home-page: https://github.com/gtnx/django-requests-panel
Author: Guillaume Thomas
Author-email: guillaume.thomas642@gmail.com
License: LICENCE.txt
Platform: UNKNOWN
